data/50-Hardsploit.rules
hardsploit/__init__.py
hardsploit/core/__init__.py
hardsploit/core/api.py
hardsploit/core/communication.py
hardsploit/core/constants.py
hardsploit/core/errors.py
hardsploit/core/firmware.py
hardsploit/core/utils.py
hardsploit/firmwares/__init__.py
hardsploit/firmwares/fpga/__init__.py
hardsploit/firmwares/fpga/can/CAN_INTERACT/HARDSPLOIT_FIRMWARE_FPGA_CAN_INTERACT.rpd
hardsploit/firmwares/fpga/can/CAN_SNIFFER/HARDSPLOIT_FIRMWARE_FPGA_CAN_SNIFFER.rpd
hardsploit/firmwares/fpga/i2c/I2C_INTERACT/HARDSPLOIT_FIRMWARE_FPGA_I2C_INTERACT.rpd
hardsploit/firmwares/fpga/spi/SPI_INTERACT/HARDSPLOIT_FIRMWARE_FPGA_SPI_INTERACT.rpd
hardsploit/firmwares/fpga/spi/SPI_SNIFFER/HARDSPLOIT_FIRMWARE_FPGA_SPI_SNIFFER.rpd
hardsploit/firmwares/fpga/swd/SWD_INTERACT/HARDSPLOIT_FIRMWARE_FPGA_SWD_INTERACT.rpd
hardsploit/firmwares/fpga/uart/UART_INTERACT/HARDSPLOIT_FIRMWARE_FPGA_UART_INTERACT.rpd
hardsploit/firmwares/fpga/version.py
hardsploit/firmwares/uc/HARDSPLOIT_FIRMWARE_UC.bin
hardsploit/firmwares/uc/__init__.py
hardsploit/firmwares/uc/version.py
hardsploit/modules/__init__.py
hardsploit/modules/can/can.py
hardsploit/modules/can/can_interact.py
hardsploit/modules/i2c/i2c.py
hardsploit/modules/i2c/i2c_sniffer.py
hardsploit/modules/spi/__init__.py
hardsploit/modules/spi/nrf24l01.py
hardsploit/modules/spi/spi.py
hardsploit/modules/spi/spi_sniffer.py
hardsploit/modules/swd/swd.py
hardsploit/modules/swd/swd_debug.py
hardsploit/modules/swd/swd_mem_ap.py
hardsploit/modules/swd/swd_stm32.py
hardsploit/modules/uart/__init__.py
hardsploit/modules/uart/uart.py
hardsploit-2.0.0.dist-info/LICENSE
hardsploit-2.0.0.dist-info/METADATA
hardsploit-2.0.0.dist-info/WHEEL
hardsploit-2.0.0.dist-info/RECORD
