Metadata-Version: 2.1
Name: hardsploit
Version: 2.0.0
Summary: API for Hardsploit HW access
Home-page: https://github.com/serma-safety-security/hardsploit
License: LGPL-3.0-only
Author: PERIES Mickaël
Author-email: m.peries@serma.com
Requires-Python: >=3.8
Classifier: License :: OSI Approved :: GNU Lesser General Public License v3 (LGPLv3)
Classifier: Operating System :: OS Independent
Classifier: Programming Language :: Python :: 3
Classifier: Programming Language :: Python :: 3.8
Classifier: Programming Language :: Python :: 3.9
Classifier: Programming Language :: Python :: 3.10
Classifier: Programming Language :: Python :: 3.11
Classifier: Programming Language :: Python :: 3.12
Requires-Dist: colorama (>=0.4.6,<0.5.0)
Requires-Dist: pyusb (>=1.2.1,<2.0.0)
Project-URL: Bug Tracker, https://github.com/serma-safety-security/hardsploit/issues
Project-URL: Documentation, https://github.com/serma-safety-security/hardsploit/wiki
